MANIFEST.in
setup.cfg
setup.py
tests/__init__.py
tests/test_widget.py
tw/__init__.py
tw/__init__.pyc
tw.dojo.egg-info/PKG-INFO
tw.dojo.egg-info/PKG-INFO.orig
tw.dojo.egg-info/SOURCES.txt
tw.dojo.egg-info/dependency_links.txt
tw.dojo.egg-info/entry_points.txt
tw.dojo.egg-info/namespace_packages.txt
tw.dojo.egg-info/not-zip-safe
tw.dojo.egg-info/requires.txt
tw.dojo.egg-info/top_level.txt
tw/dojo/__init__.py
tw/dojo/chart.py
tw/dojo/core.py
tw/dojo/data.py
tw/dojo/descriptions.py
tw/dojo/dijit.py
tw/dojo/dojo.py
tw/dojo/filepicker.py
tw/dojo/grid.py
tw/dojo/release.py
tw/dojo/selectshuttle.py
tw/dojo/tree.py
tw/dojo/static/dijit/ColorPalette.js
tw/dojo/static/dijit/Declaration.js
tw/dojo/static/dijit/Dialog.js
tw/dojo/static/dijit/Editor.js
tw/dojo/static/dijit/InlineEditBox.js
tw/dojo/static/dijit/LICENSE
tw/dojo/static/dijit/Menu.js
tw/dojo/static/dijit/ProgressBar.js
tw/dojo/static/dijit/TitlePane.js
tw/dojo/static/dijit/Toolbar.js
tw/dojo/static/dijit/Tooltip.js
tw/dojo/static/dijit/Tree.js
tw/dojo/static/dijit/_Calendar.js
tw/dojo/static/dijit/_Container.js
tw/dojo/static/dijit/_Templated.js
tw/dojo/static/dijit/_TimePicker.js
tw/dojo/static/dijit/_Widget.js
tw/dojo/static/dijit/_base.js
tw/dojo/static/dijit/dijit-all.js
tw/dojo/static/dijit/dijit.js
tw/dojo/static/dijit/dijit.js.uncompressed.js
tw/dojo/static/dijit/robot.js
tw/dojo/static/dijit/robotx.js
tw/dojo/static/dijit/_base/focus.js
tw/dojo/static/dijit/_base/manager.js
tw/dojo/static/dijit/_base/place.js
tw/dojo/static/dijit/_base/popup.js
tw/dojo/static/dijit/_base/scroll.js
tw/dojo/static/dijit/_base/sniff.js
tw/dojo/static/dijit/_base/typematic.js
tw/dojo/static/dijit/_base/wai.js
tw/dojo/static/dijit/_base/window.js
tw/dojo/static/dijit/_editor/RichText.js
tw/dojo/static/dijit/_editor/_Plugin.js
tw/dojo/static/dijit/_editor/html.js
tw/dojo/static/dijit/_editor/range.js
tw/dojo/static/dijit/_editor/selection.js
tw/dojo/static/dijit/_editor/nls/FontChoice.js
tw/dojo/static/dijit/_editor/nls/LinkDialog.js
tw/dojo/static/dijit/_editor/nls/commands.js
tw/dojo/static/dijit/_editor/nls/ar/FontChoice.js
tw/dojo/static/dijit/_editor/nls/ar/LinkDialog.js
tw/dojo/static/dijit/_editor/nls/ar/commands.js
tw/dojo/static/dijit/_editor/nls/ca/FontChoice.js
